{"depute":{"id":431,"nom":"Jean-Philippe Nilor","nom_de_famille":"Nilor","prenom":"Jean-Philippe","sexe":"H","date_naissance":"1965-05-15","lieu_naissance":"Fort-de-France (Martinique)","num_deptmt":"972","nom_circo":"Martinique","num_circo":4,"mandat_debut":"2012-06-20","groupe":{"organisme":"Gauche d\u00e9mocrate et r\u00e9publicaine","fonction":"membre"},"groupe_sigle":"GDR","parti_ratt_financier":"Mouvement Ind\u00e9pendantiste Martiniquais","responsabilites":[{"responsabilite":{"organisme":"Commission des affaires sociales","fonction":"membre"}},{"responsabilite":{"organisme":"D\u00e9l\u00e9gation aux outre-mer","fonction":"membre"}},{"responsabilite":{"organisme":"Mission d'\u00e9valuation et de contr\u00f4le des lois de financement de la s\u00e9curit\u00e9 sociale","fonction":"membre"}}],"responsabilites_extra_parlementaires":[],"groupes_parlementaires":[],"sites_web":[{"site":"http:\/\/www.jeanphilippenilor.com"}],"emails":[{"email":"jpnilor@assemblee-nationale.fr"}],"adresses":[{"adresse":"12 Rue Paul Langevin, 97228 Sainte-Luce T\u00e9l\u00e9phone : T\u00e9l\u00e9copie :"},{"adresse":"Assembl\u00e9e nationale, 126 Rue de l'Universit\u00e9, 75355 PARIS 07 SP"}],"anciens_mandats":[{"mandat":"20\/06\/2012 \/  \/ "}],"autres_mandats":[{"mandat":"Assembl\u00e9e de Martinique \/  \/ vice-pr\u00e9sident"}],"anciens_autres_mandats":[],"profession":"Collaborateur parlementaire","place_en_hemicycle":"595","url_an":"http:\/\/www2.assemblee-nationale.fr\/deputes\/fiche\/OMC_PA610654","id_an":"610654","slug":"jean-philippe-nilor","url_nosdeputes":"http:\/\/www.nosdeputes.fr\/jean-philippe-nilor","url_nosdeputes_api":"http:\/\/www.nosdeputes.fr\/jean-philippe-nilor\/json","nb_mandats":2,"twitter":""}}