{"depute":{"id":363,"nom":"V\u00e9ronique Louwagie","nom_de_famille":"Louwagie","prenom":"V\u00e9ronique","sexe":"F","date_naissance":"1961-03-20","lieu_naissance":"Buis Sur Damville (Eure)","num_deptmt":"61","nom_circo":"Orne","num_circo":2,"mandat_debut":"2012-06-20","groupe":{"organisme":"Les r\u00e9publicains","fonction":"membre"},"groupe_sigle":"LR","parti_ratt_financier":"Les R\u00e9publicains","responsabilites":[{"responsabilite":{"organisme":"Commission des finances, de l'\u00e9conomie g\u00e9n\u00e9rale et du contr\u00f4le budg\u00e9taire","fonction":"secr\u00e9taire"}}],"responsabilites_extra_parlementaires":[],"groupes_parlementaires":[{"responsabilite":{"organisme":"Groupe d'\u00e9tudes langue des signes","fonction":"vice-pr\u00e9sidente"}},{"responsabilite":{"organisme":"Groupe d'\u00e9tudes \u00c9levage","fonction":"vice-pr\u00e9sidente"}},{"responsabilite":{"organisme":"Groupe d'\u00e9tudes pme","fonction":"secr\u00e9taire"}},{"responsabilite":{"organisme":"Groupe d'amiti\u00e9 france-mongolie","fonction":"vice-pr\u00e9sidente"}},{"responsabilite":{"organisme":"Groupe d'\u00e9tudes plasturgie","fonction":"membre"}},{"responsabilite":{"organisme":"Groupe d'\u00e9tudes cheval","fonction":"vice-pr\u00e9sidente"}},{"responsabilite":{"organisme":"Groupe d'\u00e9tudes foncier","fonction":"membre"}},{"responsabilite":{"organisme":"Groupe d'\u00e9tudes chr\u00e9tiens d'orient","fonction":"secr\u00e9taire"}},{"responsabilite":{"organisme":"Groupe d'\u00e9tudes politiques de la ruralit\u00e9","fonction":"vice-pr\u00e9sidente"}},{"responsabilite":{"organisme":"Groupe d'\u00e9tudes enseignement priv\u00e9 sous contrat et hors contrat","fonction":"membre"}},{"responsabilite":{"organisme":"Groupe d'\u00e9tudes peuple tamoul","fonction":"membre"}},{"responsabilite":{"organisme":"Groupe d'amiti\u00e9 france-arabie saoudite","fonction":"secr\u00e9taire"}},{"responsabilite":{"organisme":"Groupe d'\u00e9tudes formation altern\u00e9e en milieu rural","fonction":"vice-pr\u00e9sidente"}},{"responsabilite":{"organisme":"Groupe d'amiti\u00e9 france-sri lanka","fonction":"pr\u00e9sidente"}},{"responsabilite":{"organisme":"Groupe d'\u00e9tudes enjeux du vieillissement","fonction":"membre"}},{"responsabilite":{"organisme":"Groupe d'\u00e9tudes industries agro-alimentaires et fili\u00e8re agricole","fonction":"membre"}},{"responsabilite":{"organisme":"Groupe d'\u00e9tudes biocarburants","fonction":"secr\u00e9taire"}},{"responsabilite":{"organisme":"Groupe d'\u00e9tudes chasse et territoires","fonction":"membre"}},{"responsabilite":{"organisme":"Groupe d'\u00e9tudes p\u00e9nibilit\u00e9 du travail, sant\u00e9 au travail et maladies professionnelles","fonction":"membre"}},{"responsabilite":{"organisme":"Groupe d'\u00e9tudes d\u00e9veloppement de la m\u00e9thanisation","fonction":"membre"}},{"responsabilite":{"organisme":"Groupe d'\u00e9tudes autisme","fonction":"membre"}},{"responsabilite":{"organisme":"Groupe d'\u00e9tudes commerce et artisanat","fonction":"membre"}}],"sites_web":[{"site":"http:\/\/www.veroniquelouwagie.fr"}],"emails":[{"email":"velouwagie@gmail.com"},{"email":"vlouwagie@assemblee-nationale.fr"}],"adresses":[{"adresse":"40 Rue Saint Jean 61300 L'Aigle T\u00e9l\u00e9phone :"},{"adresse":"Assembl\u00e9e nationale 126 Rue de l'Universit\u00e9 75355 Paris 07 SP"}],"anciens_mandats":[{"mandat":"20\/06\/2012 \/  \/ "}],"autres_mandats":[{"mandat":"Aigle (Orne) \/ Conseil municipal \/ maire"}],"anciens_autres_mandats":[],"profession":"Expert-comptable","place_en_hemicycle":"236","url_an":"http:\/\/www2.assemblee-nationale.fr\/deputes\/fiche\/OMC_PA608016","id_an":"608016","slug":"veronique-louwagie","url_nosdeputes":"http:\/\/www.nosdeputes.fr\/veronique-louwagie","url_nosdeputes_api":"http:\/\/www.nosdeputes.fr\/veronique-louwagie\/json","nb_mandats":2,"twitter":""}}